archive/__init__.py
archive/model/__init__.py
archive/model/rf_train_val.py
pv_vision/__init__.py
pv_vision/cell_classification/__init__.py
pv_vision/cell_classification/cnn_train_val.py
pv_vision/cell_classification/inference.py
pv_vision/cell_classification/train.py
pv_vision/crack_analysis/__init__.py
pv_vision/crack_analysis/_feature_extraction.py
pv_vision/crack_analysis/_feature_extraction_archive.py
pv_vision/crack_analysis/crackcell.py
pv_vision/defect_detection/__init__.py
pv_vision/defect_detection/draw_bbox.py
pv_vision/defect_detection/inference.py
pv_vision/defect_detection/module_classify.py
pv_vision/defect_detection/result_analysis.py
pv_vision/defect_detection/train.py
pv_vision/nn/__init__.py
pv_vision/nn/metrics.py
pv_vision/nn/modelhandler.py
pv_vision/nn/models.py
pv_vision/transform_crop/__init__.py
pv_vision/transform_crop/_cell_crop.py
pv_vision/transform_crop/_perspective_transform.py
pv_vision/transform_crop/solarmodule.py
pv_vision/transform_crop/testing/__init__.py
pv_vision/transform_crop/testing/moduleTest.py
pv_vision/transform_crop/testing/transformTest.py
pv_vision/utils/__init__.py
pv_vision/utils/color_conversion.py
pv_vision/utils/im_aug.py
pv_vision/utils/im_move.py
pv_vision/utils/im_rotate.py
pv_vision/utils/subfolder_merge.py
pv_vision/utils/supervisely_conversion.py
pv_vision-0.2.8.dist-info/LICENSE
pv_vision-0.2.8.dist-info/METADATA
pv_vision-0.2.8.dist-info/WHEEL
pv_vision-0.2.8.dist-info/top_level.txt
pv_vision-0.2.8.dist-info/RECORD
