Metadata-Version: 2.1
Name: pv_vision
Version: 0.2.8
Summary: Image analysis of defects on solar modules, including automatic detection and power loss prediction
Home-page: https://github.com/hackingmaterials/pv-vision
Author: XinChen
Author-email: chenxin0210@lbl.gov
License: BSD
Classifier: Programming Language :: Python :: 3
Classifier: License :: OSI Approved :: BSD License
Classifier: Operating System :: OS Independent
Requires-Python: >=3.10
License-File: LICENSE
Requires-Dist: imutils >=0.5.4
Requires-Dist: ipywidgets >=8.1.2
Requires-Dist: joblib >=1.2.0
Requires-Dist: matplotlib >=3.8.0
Requires-Dist: opencv-python >=4.7.0.72
Requires-Dist: scikit-learn >=1.3.0
Requires-Dist: setuptools >=68.2.2
Requires-Dist: torch >=2.2.0.post100
Requires-Dist: torchvision >=0.15.2a0
Requires-Dist: tqdm >=4.65.0
